{
  "projects": [
    {
      "id": "softcount",
      "slug": "softcount",
      "category": "web-app",
      "technologies": ["Next.js", "TypeScript", "PostgreSQL"],
      "images": [
        "/projects/softcount/screenshot-1.png",
        "/Projects/softcount/screenshot-2.png",
        "/Projects/softcount/screenshot-3.png",
        "/Projects/softcount/screenshot-4.png"
      ],
      "gradient": "from-blue-600 to-cyan-600",
      "featured": true,
      "github": null,
      "demo": null,
      "year": 2024,
      "client": "Proyecto Propio"
    },
    {
      "id": "wilson-isaza",
      "slug": "wilson-isaza",
      "category": "wordpress",
      "technologies": ["WordPress"],
      "images": [
        "/Projects/wilson-isaza/screenshot-1.png",
        "/Projects/wilson-isaza/screenshot-2.png",
        "/Projects/wilson-isaza/screenshot-3.png",
        "/Projects/wilson-isaza/screenshot-4.png"
      ],
      "gradient": "from-red-600 to-orange-600",
      "featured": true,
      "github": null,
      "demo": "https://wilsonisaza.com/",
      "year": 2024,
      "client": "Wilson Isaza - Político"
    },
    {
      "id": "empo-guzman",
      "slug": "empo-guzman",
      "category": "custom-code",
      "technologies": ["Wix"],
      "images": [
        "/Projects/empo-guzman/screenshot-1.png",
        "/Projects/empo-guzman/screenshot-2.png",
        "/Projects/empo-guzman/screenshot-3.png"
        
      ],
      "gradient": "from-indigo-600 to-purple-600",
      "featured": true,
      "github": null,
      "demo": "https://www.empoguzman.com.co/",
      "year": 2024,
      "client": "Empresas Públicas"
    },
    {
      "id": "devminds-portfolio",
      "slug": "devminds-portfolio",
      "category": "web-app",
      "technologies": ["Next.js", "TypeScript", "TailwindCSS", "Framer Motion"],
      "images": [
        "/Projects/devminds-portfolio/screenshot-1.png"
      ],
      "gradient": "from-purple-600 to-pink-600",
      "featured": true,
      "github": null,
      "demo": "https://devminds.online",
      "year": 2024,
      "client": "DevMinds"
    }
  ],
  "categories": [
    {
      "id": "all",
      "name": "All Projects"
    },
    {
      "id": "web-app",
      "name": "Web Applications"
    },
    {
      "id": "wordpress",
      "name": "WordPress"
    },
    {
      "id": "custom-code",
      "name": "Custom Code"
    },
    {
      "id": "open-source",
      "name": "Open Source"
    }
  ]
}
